<?xml version="1.0"?>

<portlet-app xmlns="http://java.sun.com/xml/ns/portlet/portlet-app_2_0.xsd" xmlns:xsi="http://www.w3.org/2001/XMLSchema-instance" xsi:schemaLocation="http://java.sun.com/xml/ns/portlet/portlet-app_2_0.xsd http://java.sun.com/xml/ns/portlet/portlet-app_2_0.xsd" version="2.0">
	<portlet>
		<portlet-name>MeMaterialCode</portlet-name>
		<display-name>MeMaterialCode</display-name>
		<portlet-class>com.liferay.util.bridges.mvc.MVCPortlet</portlet-class>
		<init-param>
			<name>view-template</name>
			<value>/view.jsp</value>
		</init-param>
		<expiration-cache>0</expiration-cache>
		<supports>
			<mime-type>text/html</mime-type>
		</supports>
		<portlet-info>
			<title>MeMaterialCode</title>
			<short-title>MeMaterialCode</short-title>
			<keywords>MeMaterialCode</keywords>
		</portlet-info>
		<security-role-ref>
			<role-name>administrator</role-name>
		</security-role-ref>
		<security-role-ref>
			<role-name>guest</role-name>
		</security-role-ref>
		<security-role-ref>
			<role-name>power-user</role-name>
		</security-role-ref>
		<security-role-ref>
			<role-name>user</role-name>
		</security-role-ref>
	</portlet>
	<portlet>
		<portlet-name>material-code</portlet-name>
		<display-name>Material Code</display-name>
		<portlet-class>com.j2eecn.mc.MaterialCodePortlet</portlet-class>
		<init-param>
			<name>view-template</name>
			<value>/html/materialcode/view.jsp</value>
		</init-param>
		<expiration-cache>0</expiration-cache>
		<supports>
			<mime-type>text/html</mime-type>
			<portlet-mode>view</portlet-mode>
		</supports>
		<resource-bundle>content.Language</resource-bundle>
		<portlet-info>
			<title>Material Code</title>
			<short-title>Material Code</short-title>
			<keywords></keywords>
		</portlet-info>
		<security-role-ref>
			<role-name>administrator</role-name>
		</security-role-ref>
		<security-role-ref>
			<role-name>guest</role-name>
		</security-role-ref>
		<security-role-ref>
			<role-name>power-user</role-name>
		</security-role-ref>
		<security-role-ref>
			<role-name>user</role-name>
		</security-role-ref>
	</portlet>
</portlet-app>